typo/Errer.py
typo/__init__.py
typo/version.py
typo/keyboardlayouts/__init__.py
typo/keyboardlayouts/en_default.py
typo-0.1.4.dist-info/LICENSE
typo-0.1.4.dist-info/METADATA
typo-0.1.4.dist-info/WHEEL
typo-0.1.4.dist-info/top_level.txt
typo-0.1.4.dist-info/RECORD
