Metadata-Version: 2.1
Name: typo
Version: 0.1.4
Summary: A python package to simulate typographical errors.
Home-page: https://github.com/ranvijaykumar/typo
Author: Ranvijay Kumar
License: MIT
Platform: UNKNOWN
Classifier: License :: OSI Approved :: MIT License
Classifier: Intended Audience :: Developers
Classifier: Intended Audience :: Information Technology
Classifier: Intended Audience :: Science/Research
Classifier: Topic :: Scientific/Engineering :: Artificial Intelligence
